lint_python/__init__.py
lint_python/__main__.py
lint_python/constants.py
lint_python/lint_python.py
lint_python-2.3.1.dist-info/METADATA
lint_python-2.3.1.dist-info/WHEEL
lint_python-2.3.1.dist-info/entry_points.txt
lint_python-2.3.1.dist-info/top_level.txt
lint_python-2.3.1.dist-info/RECORD
