Metadata-Version: 2.4
Name: lint-python
Version: 2.3.1
Summary: CLI tool used for running linter on project configured with CERT-Polska/lint-python-action
License: MIT License
Classifier: Programming Language :: Python :: 3
Requires-Dist: pyyaml
Requires-Dist: toml
